{
    "KeyPhrases": [
        {
            "Score": 0.9426549077033997,
            "Text": "RT @DefiantCrimGrad",
            "BeginOffset": 0,
            "EndOffset": 19
        },
        {
            "Score": 0.8175309300422668,
            "Text": "@AGAINSTBRATTON",
            "BeginOffset": 21,
            "EndOffset": 36
        },
        {
            "Score": 0.9369871020317078,
            "Text": "people",
            "BeginOffset": 59,
            "EndOffset": 65
        },
        {
            "Score": 0.9289131164550781,
            "Text": "court or worse",
            "BeginOffset": 82,
            "EndOffset": 96
        },
        {
            "Score": 0.9949917197227478,
            "Text": "ICE detention",
            "BeginOffset": 101,
            "EndOffset": 114
        }
    ]
}
