{
    "KeyPhrases": [
        {
            "Score": 0.9207001328468323,
            "Text": "RT @realDonaldTrump",
            "BeginOffset": 0,
            "EndOffset": 19
        },
        {
            "Score": 0.9982710480690002,
            "Text": "This country",
            "BeginOffset": 21,
            "EndOffset": 33
        },
        {
            "Score": 0.9827980995178223,
            "Text": "four more years",
            "BeginOffset": 46,
            "EndOffset": 61
        },
        {
            "Score": 0.9938278794288635,
            "Text": "Barack Obama",
            "BeginOffset": 65,
            "EndOffset": 77
        }
    ]
}
