{
    "KeyPhrases": [
        {
            "Score": 0.8537798523902893,
            "Text": "RT @alwaystheself",
            "BeginOffset": 0,
            "EndOffset": 17
        },
        {
            "Score": 0.9993479251861572,
            "Text": "A lot",
            "BeginOffset": 19,
            "EndOffset": 24
        },
        {
            "Score": 0.9997667074203491,
            "Text": "people",
            "BeginOffset": 28,
            "EndOffset": 34
        },
        {
            "Score": 0.9869934320449829,
            "Text": "an Obama-bot",
            "BeginOffset": 82,
            "EndOffset": 94
        },
        {
            "Score": 0.9975531101226807,
            "Text": "a critic",
            "BeginOffset": 98,
            "EndOffset": 106
        },
        {
            "Score": 0.9985990524291992,
            "Text": "Barack",
            "BeginOffset": 110,
            "EndOffset": 116
        },
        {
            "Score": 0.9035047292709351,
            "Text": "the Democrats",
            "BeginOffset": 118,
            "EndOffset": 131
        }
    ]
}
