{
    "KeyPhrases": [
        {
            "Score": 0.919104814529419,
            "Text": "THE SECOND AMENDMENT",
            "BeginOffset": 2,
            "EndOffset": 22
        },
        {
            "Score": 0.9563143849372864,
            "Text": "MY GUN PERMIT",
            "BeginOffset": 26,
            "EndOffset": 39
        },
        {
            "Score": 0.9435930252075195,
            "Text": "ISSUE DATE",
            "BeginOffset": 42,
            "EndOffset": 52
        },
        {
            "Score": 0.8725271821022034,
            "Text": "12/15/1791 EXPIRATION DATE",
            "BeginOffset": 54,
            "EndOffset": 80
        },
        {
            "Score": 0.7665683031082153,
            "Text": "NONE  #VETS #NRA #CCOT #TCOT",
            "BeginOffset": 82,
            "EndOffset": 110
        }
    ]
}
