{
    "KeyPhrases": [
        {
            "Score": 0.9152303338050842,
            "Text": "RT @jpodhoretz",
            "BeginOffset": 0,
            "EndOffset": 14
        },
        {
            "Score": 0.925018310546875,
            "Text": "a kid",
            "BeginOffset": 34,
            "EndOffset": 39
        },
        {
            "Score": 0.9966787695884705,
            "Text": "high school",
            "BeginOffset": 73,
            "EndOffset": 84
        },
        {
            "Score": 0.9968423247337341,
            "Text": "an 8 year sentence",
            "BeginOffset": 96,
            "EndOffset": 114
        },
        {
            "Score": 0.979332447052002,
            "Text": "trafficking",
            "BeginOffset": 119,
            "EndOffset": 130
        }
    ]
}
