{
    "KeyPhrases": [
        {
            "Score": 0.8323002457618713,
            "Text": "RT @WDFx2EU7",
            "BeginOffset": 0,
            "EndOffset": 12
        },
        {
            "Score": 0.9635353684425354,
            "Text": "@HillaryClinton",
            "BeginOffset": 15,
            "EndOffset": 30
        },
        {
            "Score": 0.9914761781692505,
            "Text": "a COMPLETE MELTDOWN",
            "BeginOffset": 41,
            "EndOffset": 60
        },
        {
            "Score": 0.9212081432342529,
            "Text": "Twitter",
            "BeginOffset": 64,
            "EndOffset": 71
        }
    ]
}
