{
    "KeyPhrases": [
        {
            "Score": 0.9606409072875977,
            "Text": "#IslamKills ISIS",
            "BeginOffset": 0,
            "EndOffset": 16
        },
        {
            "Score": 0.8858149647712708,
            "Text": "the terrorist",
            "BeginOffset": 21,
            "EndOffset": 34
        },
        {
            "Score": 0.9985553026199341,
            "Text": "SOME refugees",
            "BeginOffset": 39,
            "EndOffset": 52
        },
        {
            "Score": 0.8668177127838135,
            "Text": "ISIS",
            "BeginOffset": 57,
            "EndOffset": 61
        },
        {
            "Score": 0.5852324366569519,
            "Text": "Acceptable",
            "BeginOffset": 63,
            "EndOffset": 73
        }
    ]
}
