{
    "KeyPhrases": [
        {
            "Score": 0.8377746939659119,
            "Text": "RT @2ALAW",
            "BeginOffset": 0,
            "EndOffset": 9
        },
        {
            "Score": 0.5901631712913513,
            "Text": "Twitter",
            "BeginOffset": 11,
            "EndOffset": 18
        },
        {
            "Score": 0.5346940755844116,
            "Text": "Just Locked Me",
            "BeginOffset": 19,
            "EndOffset": 33
        },
        {
            "Score": 0.7399454712867737,
            "Text": "My Account",
            "BeginOffset": 41,
            "EndOffset": 51
        },
        {
            "Score": 0.7977242469787598,
            "Text": "Calling Mohammed A Pedophilia \n\nTwitter Straight",
            "BeginOffset": 56,
            "EndOffset": 104
        },
        {
            "Score": 0.7992676496505737,
            "Text": "Run",
            "BeginOffset": 108,
            "EndOffset": 111
        },
        {
            "Score": 0.8697992563247681,
            "Text": "Muslims \n🚫 Freedom",
            "BeginOffset": 115,
            "EndOffset": 133
        }
    ]
}
