{
    "KeyPhrases": [
        {
            "Score": 0.8354932069778442,
            "Text": "RT @Michelleg51",
            "BeginOffset": 0,
            "EndOffset": 15
        },
        {
            "Score": 0.9284542202949524,
            "Text": "@ILoveMyWife0007 #jahilc",
            "BeginOffset": 17,
            "EndOffset": 41
        },
        {
            "Score": 0.9861345887184143,
            "Text": "my son",
            "BeginOffset": 55,
            "EndOffset": 61
        },
        {
            "Score": 0.9993054866790771,
            "Text": "12years",
            "BeginOffset": 91,
            "EndOffset": 98
        },
        {
            "Score": 0.9977706670761108,
            "Text": "the justice system",
            "BeginOffset": 114,
            "EndOffset": 132
        }
    ]
}
