{
    "KeyPhrases": [
        {
            "Score": 0.936451256275177,
            "Text": "RT @PaulObrienUSA",
            "BeginOffset": 0,
            "EndOffset": 17
        },
        {
            "Score": 0.9717583656311035,
            "Text": "#Clinton",
            "BeginOffset": 22,
            "EndOffset": 30
        },
        {
            "Score": 0.9991822242736816,
            "Text": "a baby",
            "BeginOffset": 38,
            "EndOffset": 44
        },
        {
            "Score": 0.942320704460144,
            "Text": "national television @CNN &amp; #Cher",
            "BeginOffset": 48,
            "EndOffset": 84
        },
        {
            "Score": 0.9947836399078369,
            "Text": "the baby",
            "BeginOffset": 95,
            "EndOffset": 103
        }
    ]
}
