{
    "KeyPhrases": [
        {
            "Score": 0.9361827373504639,
            "Text": "RT @Payetsu",
            "BeginOffset": 0,
            "EndOffset": 11
        },
        {
            "Score": 0.9937649369239807,
            "Text": "the solution",
            "BeginOffset": 18,
            "EndOffset": 30
        },
        {
            "Score": 0.9871495962142944,
            "Text": "all my problems",
            "BeginOffset": 34,
            "EndOffset": 49
        },
        {
            "Score": 0.9959486722946167,
            "Text": "the problem",
            "BeginOffset": 59,
            "EndOffset": 70
        },
        {
            "Score": 0.9873969554901123,
            "Text": "all my solutions",
            "BeginOffset": 74,
            "EndOffset": 90
        }
    ]
}
