{
    "KeyPhrases": [
        {
            "Score": 0.9241095185279846,
            "Text": "RT @DragonflyJonez",
            "BeginOffset": 0,
            "EndOffset": 18
        },
        {
            "Score": 0.9890896081924438,
            "Text": "a remake",
            "BeginOffset": 35,
            "EndOffset": 43
        },
        {
            "Score": 0.9981464147567749,
            "Text": "The Wash",
            "BeginOffset": 47,
            "EndOffset": 55
        },
        {
            "Score": 0.9945535659790039,
            "Text": "Ross and Gucci",
            "BeginOffset": 61,
            "EndOffset": 75
        }
    ]
}
