{
    "KeyPhrases": [
        {
            "Score": 0.7927285432815552,
            "Text": "RT @Taxpayers1234",
            "BeginOffset": 0,
            "EndOffset": 17
        },
        {
            "Score": 0.9432017207145691,
            "Text": "@Olivianuzzi Hillary",
            "BeginOffset": 19,
            "EndOffset": 39
        },
        {
            "Score": 0.9875816702842712,
            "Text": "Americans",
            "BeginOffset": 45,
            "EndOffset": 54
        },
        {
            "Score": 0.9895401000976562,
            "Text": "#Benghazi",
            "BeginOffset": 81,
            "EndOffset": 90
        }
    ]
}
