{
    "KeyPhrases": [
        {
            "Score": 0.9087198376655579,
            "Text": "RT @shadowandact",
            "BeginOffset": 0,
            "EndOffset": 16
        },
        {
            "Score": 0.9580168128013611,
            "Text": "2 Flint water crisis projects",
            "BeginOffset": 28,
            "EndOffset": 57
        },
        {
            "Score": 0.996173620223999,
            "Text": "the works",
            "BeginOffset": 61,
            "EndOffset": 70
        },
        {
            "Score": 0.8687453866004944,
            "Text": "one scripted",
            "BeginOffset": 83,
            "EndOffset": 95
        },
        {
            "Score": 0.6916818618774414,
            "Text": "&amp;",
            "BeginOffset": 122,
            "EndOffset": 127
        },
        {
            "Score": 0.967357337474823,
            "Text": "one doc",
            "BeginOffset": 128,
            "EndOffset": 135
        },
        {
            "Score": 0.9573692083358765,
            "Text": "https",
            "BeginOffset": 137,
            "EndOffset": 142
        }
    ]
}
