{
    "KeyPhrases": [
        {
            "Score": 0.7349953651428223,
            "Text": "RT @kylegriffin",
            "BeginOffset": 0,
            "EndOffset": 15
        },
        {
            "Score": 0.9302467703819275,
            "Text": "1",
            "BeginOffset": 15,
            "EndOffset": 16
        },
        {
            "Score": 0.9972031116485596,
            "Text": "Kellyanne Conway",
            "BeginOffset": 18,
            "EndOffset": 34
        },
        {
            "Score": 0.9981878399848938,
            "Text": "Kaine",
            "BeginOffset": 40,
            "EndOffset": 45
        },
        {
            "Score": 0.9195241928100586,
            "Text": "female moderator",
            "BeginOffset": 75,
            "EndOffset": 91
        },
        {
            "Score": 0.7850534915924072,
            "Text": "Trump",
            "BeginOffset": 101,
            "EndOffset": 106
        }
    ]
}
