{
    "KeyPhrases": [
        {
            "Score": 0.9036632180213928,
            "Text": "RT @gerfingerpoken",
            "BeginOffset": 0,
            "EndOffset": 18
        },
        {
            "Score": 0.8705316781997681,
            "Text": "North Carolina Correct",
            "BeginOffset": 20,
            "EndOffset": 42
        },
        {
            "Score": 0.9643856287002563,
            "Text": "Transgender Restrooms",
            "BeginOffset": 44,
            "EndOffset": 65
        },
        {
            "Score": 0.8118890523910522,
            "Text": "Civil Right",
            "BeginOffset": 70,
            "EndOffset": 81
        },
        {
            "Score": 0.8343639373779297,
            "Text": "American Thinker",
            "BeginOffset": 84,
            "EndOffset": 100
        }
    ]
}
