{
    "KeyPhrases": [
        {
            "Score": 0.9392686486244202,
            "Text": "RT @SheriffClarke",
            "BeginOffset": 0,
            "EndOffset": 17
        },
        {
            "Score": 0.9364626407623291,
            "Text": "a problem opening",
            "BeginOffset": 28,
            "EndOffset": 45
        },
        {
            "Score": 0.9801767468452454,
            "Text": "this one",
            "BeginOffset": 51,
            "EndOffset": 59
        },
        {
            "Score": 0.9177467226982117,
            "Text": "Zero tolerance",
            "BeginOffset": 61,
            "EndOffset": 75
        },
        {
            "Score": 0.984326183795929,
            "Text": "Sanctuary Cities",
            "BeginOffset": 80,
            "EndOffset": 96
        }
    ]
}
