{
    "KeyPhrases": [
        {
            "Score": 0.9221685528755188,
            "Text": "RT @tgradous",
            "BeginOffset": 0,
            "EndOffset": 12
        },
        {
            "Score": 0.9393428564071655,
            "Text": "Fmr #PlannedParenthood Manager",
            "BeginOffset": 14,
            "EndOffset": 44
        },
        {
            "Score": 0.9225756525993347,
            "Text": "#PP Views Women",
            "BeginOffset": 50,
            "EndOffset": 65
        },
        {
            "Score": 0.9670279622077942,
            "Text": "Bodies",
            "BeginOffset": 68,
            "EndOffset": 74
        },
        {
            "Score": 0.8346641063690186,
            "Text": "Profit Centers",
            "BeginOffset": 79,
            "EndOffset": 93
        },
        {
            "Score": 0.8651554584503174,
            "Text": "'\n@LLMajer @LVNancy @lukiOC @JVER1",
            "BeginOffset": 93,
            "EndOffset": 127
        }
    ]
}
