{
    "KeyPhrases": [
        {
            "Score": 0.8561639189720154,
            "Text": "RT @MattMurph24",
            "BeginOffset": 0,
            "EndOffset": 15
        },
        {
            "Score": 0.9989080429077148,
            "Text": "Francois",
            "BeginOffset": 17,
            "EndOffset": 25
        },
        {
            "Score": 0.9803163409233093,
            "Text": "some protection",
            "BeginOffset": 30,
            "EndOffset": 45
        },
        {
            "Score": 0.9804219007492065,
            "Text": "Wake",
            "BeginOffset": 57,
            "EndOffset": 61
        }
    ]
}
