{
    "KeyPhrases": [
        {
            "Score": 0.9313379526138306,
            "Text": "RT @mcuban",
            "BeginOffset": 0,
            "EndOffset": 10
        },
        {
            "Score": 0.9986820816993713,
            "Text": "Donald Trump",
            "BeginOffset": 15,
            "EndOffset": 27
        },
        {
            "Score": 0.9877200722694397,
            "Text": "more than 0mm",
            "BeginOffset": 33,
            "EndOffset": 46
        },
        {
            "Score": 0.9974267482757568,
            "Text": "daddy",
            "BeginOffset": 50,
            "EndOffset": 55
        },
        {
            "Score": 0.9924119710922241,
            "Text": "money",
            "BeginOffset": 58,
            "EndOffset": 63
        },
        {
            "Score": 0.9995311498641968,
            "Text": "the age",
            "BeginOffset": 67,
            "EndOffset": 74
        },
        {
            "Score": 0.9989803433418274,
            "Text": "33",
            "BeginOffset": 78,
            "EndOffset": 80
        },
        {
            "Score": 0.9788125157356262,
            "Text": "3rd base",
            "BeginOffset": 90,
            "EndOffset": 98
        },
        {
            "Score": 0.9319300055503845,
            "Text": "1st",
            "BeginOffset": 112,
            "EndOffset": 115
        }
    ]
}
