{
    "KeyPhrases": [
        {
            "Score": 0.9386676549911499,
            "Text": "RT @NYC_Everyday",
            "BeginOffset": 0,
            "EndOffset": 16
        },
        {
            "Score": 0.9964284896850586,
            "Text": "Bruce Jenner",
            "BeginOffset": 18,
            "EndOffset": 30
        },
        {
            "Score": 0.993121862411499,
            "Text": "ABC ratings",
            "BeginOffset": 38,
            "EndOffset": 49
        },
        {
            "Score": 0.7047520875930786,
            "Text": "millions",
            "BeginOffset": 53,
            "EndOffset": 61
        }
    ]
}
