{
    "KeyPhrases": [
        {
            "Score": 0.934899628162384,
            "Text": "RT @BPDmisconduct",
            "BeginOffset": 0,
            "EndOffset": 17
        },
        {
            "Score": 0.971558153629303,
            "Text": "Mount Vernon police officer",
            "BeginOffset": 19,
            "EndOffset": 46
        },
        {
            "Score": 0.8777673840522766,
            "Text": "shooting",
            "BeginOffset": 58,
            "EndOffset": 66
        },
        {
            "Score": 0.6958600282669067,
            "Text": "standoff",
            "BeginOffset": 68,
            "EndOffset": 76
        }
    ]
}
