{
    "KeyPhrases": [
        {
            "Score": 0.940019428730011,
            "Text": "RT @Seattle_Post",
            "BeginOffset": 0,
            "EndOffset": 16
        },
        {
            "Score": 0.717153012752533,
            "Text": "N.Y. prison escapee",
            "BeginOffset": 18,
            "EndOffset": 37
        },
        {
            "Score": 0.9570379257202148,
            "Text": "other inmate",
            "BeginOffset": 52,
            "EndOffset": 64
        }
    ]
}
