{
    "KeyPhrases": [
        {
            "Score": 0.9311826229095459,
            "Text": "RT @SkuzzNews",
            "BeginOffset": 0,
            "EndOffset": 13
        },
        {
            "Score": 0.8666427731513977,
            "Text": "Clinton",
            "BeginOffset": 39,
            "EndOffset": 46
        },
        {
            "Score": 0.7016649842262268,
            "Text": "#ClintonHate #deplorablelivesmatter #BillRapesEverydayAmericans https://t.co/ARjWx",
            "BeginOffset": 57,
            "EndOffset": 139
        }
    ]
}
