{
    "KeyPhrases": [
        {
            "Score": 0.942589282989502,
            "Text": "RT @SadatX",
            "BeginOffset": 0,
            "EndOffset": 10
        },
        {
            "Score": 0.8941993117332458,
            "Text": "Shoutout",
            "BeginOffset": 12,
            "EndOffset": 20
        },
        {
            "Score": 0.9548019170761108,
            "Text": "the Lovely @maryjane1love",
            "BeginOffset": 24,
            "EndOffset": 49
        },
        {
            "Score": 0.9656627178192139,
            "Text": "our @SadatXWine collab T-Shirt",
            "BeginOffset": 62,
            "EndOffset": 92
        }
    ]
}
