{
    "KeyPhrases": [
        {
            "Score": 0.9024336338043213,
            "Text": "RT @Ian56789",
            "BeginOffset": 0,
            "EndOffset": 12
        },
        {
            "Score": 0.6903989911079407,
            "Text": "Chinese",
            "BeginOffset": 14,
            "EndOffset": 21
        },
        {
            "Score": 0.6897971034049988,
            "Text": "Germans",
            "BeginOffset": 23,
            "EndOffset": 30
        },
        {
            "Score": 0.9565171599388123,
            "Text": "Abandoned Nuclear Wasteland",
            "BeginOffset": 47,
            "EndOffset": 74
        },
        {
            "Score": 0.8414515256881714,
            "Text": "Chernobyl",
            "BeginOffset": 78,
            "EndOffset": 87
        }
    ]
}
