{
    "KeyPhrases": [
        {
            "Score": 0.949055016040802,
            "Text": "RT @BocaLegend",
            "BeginOffset": 0,
            "EndOffset": 14
        },
        {
            "Score": 0.9908044338226318,
            "Text": "Another company",
            "BeginOffset": 16,
            "EndOffset": 31
        },
        {
            "Score": 0.9514598250389099,
            "Text": "move",
            "BeginOffset": 42,
            "EndOffset": 46
        },
        {
            "Score": 0.9840779304504395,
            "Text": "Mexico",
            "BeginOffset": 50,
            "EndOffset": 56
        },
        {
            "Score": 0.9990320205688477,
            "Text": "Trump",
            "BeginOffset": 58,
            "EndOffset": 63
        },
        {
            "Score": 0.7433207631111145,
            "Text": "employees count",
            "BeginOffset": 80,
            "EndOffset": 95
        }
    ]
}
