{
    "KeyPhrases": [
        {
            "Score": 0.9388778805732727,
            "Text": "RT @PolincoNews",
            "BeginOffset": 0,
            "EndOffset": 15
        },
        {
            "Score": 0.9671693444252014,
            "Text": "BREAKING",
            "BeginOffset": 17,
            "EndOffset": 25
        },
        {
            "Score": 0.945888340473175,
            "Text": "Nation",
            "BeginOffset": 27,
            "EndOffset": 33
        },
        {
            "Score": 0.9817748069763184,
            "Text": "’s Largest Police Union Endorses Donald Trump",
            "BeginOffset": 33,
            "EndOffset": 78
        },
        {
            "Score": 0.985130250453949,
            "Text": "President",
            "BeginOffset": 83,
            "EndOffset": 92
        },
        {
            "Score": 0.9971622824668884,
            "Text": "The Fraternal Order",
            "BeginOffset": 94,
            "EndOffset": 113
        },
        {
            "Score": 0.9156452417373657,
            "Text": "Police",
            "BeginOffset": 117,
            "EndOffset": 123
        }
    ]
}
