{
    "KeyPhrases": [
        {
            "Score": 0.9278837442398071,
            "Text": "RT @Gorimaslo",
            "BeginOffset": 0,
            "EndOffset": 13
        },
        {
            "Score": 0.4193439185619354,
            "Text": "AWESOME",
            "BeginOffset": 15,
            "EndOffset": 22
        },
        {
            "Score": 0.7038983106613159,
            "Text": "Trump Stops",
            "BeginOffset": 24,
            "EndOffset": 35
        },
        {
            "Score": 0.8419555425643921,
            "Text": "Cheesesteaks and Connects",
            "BeginOffset": 44,
            "EndOffset": 69
        },
        {
            "Score": 0.854306161403656,
            "Text": "Undecided Voters https://t.co/9JhLx1OHP9 #TrumpP",
            "BeginOffset": 75,
            "EndOffset": 123
        }
    ]
}
