{
    "KeyPhrases": [
        {
            "Score": 0.9433509111404419,
            "Text": "RT @TyFancher",
            "BeginOffset": 0,
            "EndOffset": 13
        },
        {
            "Score": 0.9475923180580139,
            "Text": "Factory Owner Kills Children",
            "BeginOffset": 15,
            "EndOffset": 43
        },
        {
            "Score": 0.7229291796684265,
            "Text": "#4Words",
            "BeginOffset": 44,
            "EndOffset": 51
        }
    ]
}
