{
    "KeyPhrases": [
        {
            "Score": 0.9905607104301453,
            "Text": "Trump",
            "BeginOffset": 26,
            "EndOffset": 31
        },
        {
            "Score": 0.9840366840362549,
            "Text": "the most pro-veteran candidate",
            "BeginOffset": 35,
            "EndOffset": 65
        },
        {
            "Score": 0.716850757598877,
            "Text": "#Trump2016",
            "BeginOffset": 67,
            "EndOffset": 77
        }
    ]
}
