{
    "KeyPhrases": [
        {
            "Score": 0.9546446800231934,
            "Text": "RT @A_M_Perez",
            "BeginOffset": 0,
            "EndOffset": 13
        },
        {
            "Score": 0.8822098970413208,
            "Text": "deep rooted evil",
            "BeginOffset": 24,
            "EndOffset": 40
        },
        {
            "Score": 0.9975262880325317,
            "Text": "a mother",
            "BeginOffset": 51,
            "EndOffset": 59
        },
        {
            "Score": 0.9987261295318604,
            "Text": "kids",
            "BeginOffset": 65,
            "EndOffset": 69
        },
        {
            "Score": 0.99641352891922,
            "Text": "Jet Blue",
            "BeginOffset": 73,
            "EndOffset": 81
        },
        {
            "Score": 0.9983311295509338,
            "Text": "her father",
            "BeginOffset": 99,
            "EndOffset": 109
        },
        {
            "Score": 0.8215948343276978,
            "Text": "@IvankaTrump @MattLasner\n#M",
            "BeginOffset": 112,
            "EndOffset": 139
        }
    ]
}
