{
    "KeyPhrases": [
        {
            "Score": 0.9207767248153687,
            "Text": "RT @steph_bello",
            "BeginOffset": 0,
            "EndOffset": 15
        },
        {
            "Score": 0.8081769347190857,
            "Text": "@VanJones68 @ananavarro Trump questions",
            "BeginOffset": 17,
            "EndOffset": 56
        },
        {
            "Score": 0.9985433220863342,
            "Text": "a grieving mother",
            "BeginOffset": 65,
            "EndOffset": 82
        },
        {
            "Score": 0.999350905418396,
            "Text": "his own wife",
            "BeginOffset": 110,
            "EndOffset": 122
        }
    ]
}
