{
    "KeyPhrases": [
        {
            "Score": 0.9543583989143372,
            "Text": "RT @ConsvInCali",
            "BeginOffset": 0,
            "EndOffset": 15
        },
        {
            "Score": 0.9878445267677307,
            "Text": "Dem lawmaker",
            "BeginOffset": 48,
            "EndOffset": 60
        },
        {
            "Score": 0.9559829235076904,
            "Text": "Hillary pin",
            "BeginOffset": 67,
            "EndOffset": 78
        },
        {
            "Score": 0.9963024258613586,
            "Text": "probe",
            "BeginOffset": 86,
            "EndOffset": 91
        },
        {
            "Score": 0.9970916509628296,
            "Text": "Clinton",
            "BeginOffset": 97,
            "EndOffset": 104
        },
        {
            "Score": 0.66641765832901,
            "Text": "emails",
            "BeginOffset": 107,
            "EndOffset": 113
        }
    ]
}
