{
    "KeyPhrases": [
        {
            "Score": 0.9409725666046143,
            "Text": "RT @SaxxSkwerl",
            "BeginOffset": 0,
            "EndOffset": 14
        },
        {
            "Score": 0.7459579110145569,
            "Text": "Wrong",
            "BeginOffset": 16,
            "EndOffset": 21
        },
        {
            "Score": 0.9932669401168823,
            "Text": "a verified conflict",
            "BeginOffset": 45,
            "EndOffset": 64
        },
        {
            "Score": 0.9992017149925232,
            "Text": "interest",
            "BeginOffset": 68,
            "EndOffset": 76
        },
        {
            "Score": 0.753501832485199,
            "Text": "Do u",
            "BeginOffset": 78,
            "EndOffset": 82
        },
        {
            "Score": 0.9821725487709045,
            "Text": "ANY scruples",
            "BeginOffset": 88,
            "EndOffset": 100
        },
        {
            "Score": 0.9894388318061829,
            "Text": "A shred",
            "BeginOffset": 109,
            "EndOffset": 116
        },
        {
            "Score": 0.9927853345870972,
            "Text": "ethics",
            "BeginOffset": 120,
            "EndOffset": 126
        }
    ]
}
